src/__init__.py
src/app.py
src/lib/Argument.py
src/lib/__init__.py
Encryption_and_decryption-0.0.1.dist-info/METADATA
Encryption_and_decryption-0.0.1.dist-info/WHEEL
Encryption_and_decryption-0.0.1.dist-info/entry_points.txt
Encryption_and_decryption-0.0.1.dist-info/top_level.txt
Encryption_and_decryption-0.0.1.dist-info/RECORD
