Metadata-Version: 2.1
Name: Encryption_and_decryption
Version: 0.0.1
Summary: Encryption_and_decryption Methods in Python
Home-page: https://git.selfmade.ninja/SRIDHARDSCV/encryption_and_decryption
Author: Sridhar
Author-email: dcsvsridhar@gmail.com
License: UNKNOWN
Platform: UNKNOWN
